hydrothings/__init__.py
hydrothings/engine.py
hydrothings/main.py
hydrothings/middleware.py
hydrothings/schemas.py
hydrothings/settings.py
hydrothings/utils.py
hydrothings/validators.py
hydrothings/backends/__init__.py
hydrothings/backends/frostserver/__init__.py
hydrothings/backends/frostserver/apps.py
hydrothings/backends/frostserver/engine.py
hydrothings/backends/frostserver/renderers.py
hydrothings/backends/frostserver/urls.py
hydrothings/backends/odm2/__init__.py
hydrothings/backends/odm2/apps.py
hydrothings/backends/odm2/engine.py
hydrothings/backends/odm2/models.py
hydrothings/backends/odm2/schemas.py
hydrothings/backends/odm2/urls.py
hydrothings/backends/sensorthings/__init__.py
hydrothings/backends/sensorthings/apps.py
hydrothings/backends/sensorthings/engine.py
hydrothings/backends/sensorthings/models.py
hydrothings/backends/sensorthings/urls.py
hydrothings/components/__init__.py
hydrothings/components/datastreams/__init__.py
hydrothings/components/datastreams/schemas.py
hydrothings/components/datastreams/views.py
hydrothings/components/featuresofinterest/__init__.py
hydrothings/components/featuresofinterest/schemas.py
hydrothings/components/featuresofinterest/views.py
hydrothings/components/historicallocations/__init__.py
hydrothings/components/historicallocations/schemas.py
hydrothings/components/historicallocations/views.py
hydrothings/components/locations/__init__.py
hydrothings/components/locations/schemas.py
hydrothings/components/locations/views.py
hydrothings/components/observations/__init__.py
hydrothings/components/observations/schemas.py
hydrothings/components/observations/utils.py
hydrothings/components/observations/views.py
hydrothings/components/observedproperties/__init__.py
hydrothings/components/observedproperties/schemas.py
hydrothings/components/observedproperties/views.py
hydrothings/components/root/__init__.py
hydrothings/components/root/schemas.py
hydrothings/components/root/views.py
hydrothings/components/sensors/__init__.py
django_hydrothings-0.1.7.dist-info/LICENSE.txt
django_hydrothings-0.1.7.dist-info/METADATA
django_hydrothings-0.1.7.dist-info/WHEEL
django_hydrothings-0.1.7.dist-info/top_level.txt
django_hydrothings-0.1.7.dist-info/zip-safe
django_hydrothings-0.1.7.dist-info/RECORD
