Metadata-Version: 2.1
Name: django-hydrothings
Version: 0.1.7
License-File: LICENSE.txt
Requires-Dist: django (>=2.2)
Requires-Dist: django-ninja (>=0.20.0)
Requires-Dist: pydantic (<2.0.0,>=1.6)
Requires-Dist: geojson-pydantic (>=0.5.0)
Requires-Dist: requests (>=2)
Requires-Dist: odata-query (>=0.8.1)
Requires-Dist: pytz (>=2022.7.1)
Requires-Dist: python-dateutil (>=2.8.2)
Provides-Extra: docs
Requires-Dist: sphinx-autodoc-typehints ; extra == 'docs'
